[
  {
    "id": "v1",
    "name": "Alex Johnson",
    "skills": [
      "python",
      "data analysis",
      "web development"
    ],
    "interest": "machine learning",
    "location": {
      "lat": 37.7749,
      "lng": -122.4194
    }
  },
  {
    "id": "v2",
    "name": "Priya Sharma",
    "skills": [
      "graphic design",
      "marketing",
      "social media"
    ],
    "interest": "community outreach",
    "location": {
      "lat": 40.7128,
      "lng": -74.006
    }
  },
  {
    "id": "v3",
    "name": "Marcus Lee",
    "skills": [
      "teaching",
      "tutoring",
      "mathematics"
    ],
    "interest": "education",
    "location": {
      "lat": 34.0522,
      "lng": -118.2437
    }
  },
  {
    "id": "v4",
    "name": "Fatima Ali",
    "skills": [
      "healthcare",
      "first aid",
      "elderly care"
    ],
    "interest": "nursing",
    "location": {
      "lat": 29.7604,
      "lng": -95.3698
    }
  },
  {
    "id": "v5",
    "name": "Jordan Taylor",
    "skills": [
      "gardening",
      "sustainability",
      "community organizing"
    ],
    "interest": "environmental conservation",
    "location": {
      "lat": 47.6062,
      "lng": -122.3321
    }
  }
]